rtl/half_adder.v
module half_adder(
    input A,
    input B,
    output carry,
    output sum
);

    and and1(carry, A, B);
    xor xor1(sum, A, B);

endmodule // half_adder

rtl/full_adder.v
module full_adder(
    input A,
    input B,
    input C,
    output carry,
    output sum
);

    wire sum1;
    wire carry1;
    wire carry2;

    // Instantiate the adder
    half_adder half_adder_1(
        .A(B),
        .B(C),
        .sum(sum1),
        .carry(carry1)
    );

    half_adder half_adder_2(
        .A(A),
        .B(sum1),
        .sum(sum),
        .carry(carry2)
    );

    or or1(carry, carry2, carry1);

endmodule // full_adder

tb/full_adder_tb.v
`timescale 1ns / 1ns
`include "../rtl/full_adder.v"
`include "../rtl/half_adder.v"

module full_adder_tb;

reg A;
reg B;
reg C;
wire carry;
wire sum;

full_adder uut(A, B, C, carry, sum);

initial begin

    $dumpfile("../sim/full_adder.vcd");
    $dumpvars(0, full_adder_tb);

    {A, B, C} = 3'd0; #20;
    {A, B, C} = 3'd1; #20;
    {A, B, C} = 3'd2; #20;
    {A, B, C} = 3'd3; #20;
    {A, B, C} = 3'd4; #20;
    {A, B, C} = 3'd5; #20;
    {A, B, C} = 3'd6; #20;
    {A, B, C} = 3'd7; #20;


    $display("test completed!");

end

endmodule // full_adder

sim/full_adder.vcd
$date
	Sun Jan 11 22:39:11 2026
$end
$version
	Icarus Verilog
$end
$timescale
	1ns
$end
$scope module full_adder_tb $end
$var wire 1 ! sum $end
$var wire 1 " carry $end
$var reg 1 # A $end
$var reg 1 $ B $end
$var reg 1 % C $end
$scope module uut $end
$var wire 1 # A $end
$var wire 1 $ B $end
$var wire 1 % C $end
$var wire 1 " carry $end
$var wire 1 & sum1 $end
$var wire 1 ! sum $end
$var wire 1 ' carry2 $end
$var wire 1 ( carry1 $end
$scope module half_adder_1 $end
$var wire 1 $ A $end
$var wire 1 % B $end
$var wire 1 ( carry $end
$var wire 1 & sum $end
$upscope $end
$scope module half_adder_2 $end
$var wire 1 # A $end
$var wire 1 & B $end
$var wire 1 ' carry $end
$var wire 1 ! sum $end
$upscope $end
$upscope $end
$upscope $end
$enddefinitions $end
$comment Show the parameter values. $end
$dumpall
$end
#0
$dumpvars
0(
0'
0&
0%
0$
0#
0"
0!
$end
#20
1!
1&
1%
#40
1$
0%
#60
1"
0!
1(
0&
1%
#80
0"
1!
0(
1#
0$
0%
#100
1"
1'
0!
1&
1%
#120
1$
0%
#140
0'
1!
1(
0&
1%
