rtl/mux.v
module mux(
    input A,
    input B,
    input sel,
    output out
);

    not not1(not1Out, sel);
    and and1(and1Out, A, not1Out);
    and and2(and2Out, B, sel);
    or or1(out, and1Out, and2Out);

endmodule // mux

tb/mux_tb.v
`timescale 1ns / 1ns
`include "../rtl/mux.v"

module mux_tb;

reg A;
reg B;
reg sel;
wire out;

mux uut(A, B, sel, out);

initial begin

    $dumpfile("../sim/mux.vcd");
    $dumpvars(0, mux_tb);

    {A, B, sel} = 3'd0; #20; 
    {A, B, sel} = 3'd1; #20; 
    {A, B, sel} = 3'd2; #20; 
    {A, B, sel} = 3'd3; #20; 
    {A, B, sel} = 3'd4; #20; 
    {A, B, sel} = 3'd5; #20; 
    {A, B, sel} = 3'd6; #20; 
    {A, B, sel} = 3'd7; #20; 
    $display("test completed");

end

endmodule // mux_tb

sim/mux_tb.vcd
$date
	Sat Jan 10 16:52:24 2026
$end
$version
	Icarus Verilog
$end
$timescale
	1ns
$end
$scope module mux_tb $end
$var wire 1 ! out $end
$var reg 1 " A $end
$var reg 1 # B $end
$var reg 1 $ sel $end
$scope module uut $end
$var wire 1 " A $end
$var wire 1 # B $end
$var wire 1 % and1Out $end
$var wire 1 & and2Out $end
$var wire 1 ' not1Out $end
$var wire 1 ! out $end
$var wire 1 $ sel $end
$upscope $end
$upscope $end
$enddefinitions $end
$comment Show the parameter values. $end
$dumpall
$end
#0
$dumpvars
1'
0&
0%
0$
0#
0"
0!
$end
#20
0'
1$
#40
1'
1#
0$
#60
1!
0'
1&
1$
#80
1%
1'
0&
1"
0#
0$
#100
0!
0%
0'
1$
#120
1!
1%
1'
1#
0$
#140
0%
0'
1&
1$
