rtl/register16.v
module register16 (
    input wire clk,         
    input wire rst,    
    input wire load,      
    input wire [15:0] in,   
    output reg [15:0] out  // register since it holds state
);

    // Trigger on the rising edge of the clock or the reset
    always @(posedge clk or posedge rst) begin
        if (rst) begin
            // Asynchronous Reset: Clear output to 0
            out <= 16'b0;
        end 
        else if (load) begin
            // If load is high, update output with input data
            out <= in;
        end
        // If load is low, d_out maintains its previous value automatically
    end

endmodule

tb/register16_tb.v
`timescale 1ns / 1ns
`include "../rtl/register16.v"

module register16_tb;

    reg clk;
    reg rst;
    reg load;
    reg[15:0] in;
    wire[15:0] out;

    register16 uut(
        .clk(clk),
        .rst(rst),
        .load(load),
        .in(in),
        .out(out)
    );

    always #10 clk = ~clk; //toggle the clock ever 5 ns

    initial begin

        $dumpfile("../sim/register16.vcd");
        $dumpvars(0, register16_tb);

        clk = 0;

        rst = 1; #10;
        rst = 0; #10;

        load = 1; #10;
        in = 16'd123; #10;
        load = 0; #10;
        in = 16'd0; #10;

        rst = 1; #10;
        rst = 0; #10;

        $display("Testing complete!");

        $finish; // need to have this to tell the clock to stop

    end


endmodule // register_tb

sim/register16.vcd
$date
	Mon Jan 12 20:48:29 2026
$end
$version
	Icarus Verilog
$end
$timescale
	1ns
$end
$scope module register16_tb $end
$var wire 16 ! out [15:0] $end
$var reg 1 " clk $end
$var reg 16 # in [15:0] $end
$var reg 1 $ load $end
$var reg 1 % rst $end
$scope module uut $end
$var wire 1 " clk $end
$var wire 16 & in [15:0] $end
$var wire 1 $ load $end
$var wire 1 % rst $end
$var reg 16 ' out [15:0] $end
$upscope $end
$upscope $end
$enddefinitions $end
$comment Show the parameter values. $end
$dumpall
$end
#0
$dumpvars
b0 '
bx &
1%
x$
bx #
0"
b0 !
$end
#5
1"
#10
0"
0%
#15
1"
#20
0"
1$
#25
bx !
bx '
1"
#30
0"
b1111011 #
b111101#496895660
11011 !
b1111011 '
1"
#40
0"
0$
#45
1"
#50
0"
b0 #
b0 &
#55
1"
#60
b0 !
b0 '
0"
1%
#65
1"
#70
0"
0%
